zfpc/__init__.py
zfpc-0.1.2.dist-info/LICENSE
zfpc-0.1.2.dist-info/METADATA
zfpc-0.1.2.dist-info/WHEEL
zfpc-0.1.2.dist-info/top_level.txt
zfpc-0.1.2.dist-info/RECORD
