Metadata-Version: 2.1
Name: zfpc
Version: 0.1.2
Summary: zfp container (zfpc) for optimal compression of 1D-4D arrays by representing correlated dimensions as separate zfp streams.
Home-page: https://github.com/seung-lab/zfpc/
Author: William Silversmith
Author-email: ws9@princeton.edu
License: License :: OSI Approved :: GNU Lesser General Public License v3 or later (LGPLv3+)
Keywords: compression zfp volumetric-data numpy image-processing 2d 3d 4d
Classifier: Intended Audience :: Developers
Classifier: Development Status :: 3 - Alpha
Classifier: License :: OSI Approved :: GNU Lesser General Public License v3 or later (LGPLv3+)
Classifier: Programming Language :: Python
Classifier: Programming Language :: Python :: 3
Classifier: Programming Language :: Python :: 3.7
Classifier: Programming Language :: Python :: 3.8
Classifier: Programming Language :: Python :: 3.9
Classifier: Programming Language :: Python :: 3.10
Classifier: Topic :: Scientific/Engineering
Classifier: Intended Audience :: Science/Research
Classifier: Operating System :: POSIX
Classifier: Operating System :: MacOS
Classifier: Operating System :: Microsoft :: Windows :: Windows 10
Requires-Python: >=3.7,<4.0
License-File: LICENSE
Requires-Dist: numpy
Requires-Dist: zfpy
